dbtlogs/__init__.py
dbtlogs/main.py
dbtlogs_prebuild-0.5.dist-info/METADATA
dbtlogs_prebuild-0.5.dist-info/WHEEL
dbtlogs_prebuild-0.5.dist-info/entry_points.txt
dbtlogs_prebuild-0.5.dist-info/top_level.txt
dbtlogs_prebuild-0.5.dist-info/RECORD
